{"data_mtime":1745121503,"dep_lines":[32,33,34,35,36,37,38,39,40,25,26,27,28,29,30,31,32,35,37,41,42,17,25,15,18,19,20,21,23,1,1,1,1,1,1,1,1,1,1,1],"dep_prios":[10,10,10,10,10,10,5,5,5,10,10,10,10,10,10,10,20,20,20,5,5,5,20,5,10,5,10,5,10,5,20,20,30,30,30,30,30,30,30,30],"dependencies":["jax._src.interpreters.ad","jax._src.interpreters.mlir","jax._src.interpreters.partial_eval","jax._src.lax.lax","jax._src.lax.slicing","jax._src.state.indexing","jax._src.state.types","jax._src.state.primitives","jax._src.state.utils","jax._src.api_util","jax._src.ad_util","jax._src.config","jax._src.core","jax._src.linear_util","jax._src.source_info_util","jax._src.tree_util","jax._src.interpreters","jax._src.lax","jax._src.state","jax._src.typing","jax._src.util","collections.abc","jax._src","__future__","dataclasses","functools","operator","typing","numpy","builtins","pyexpat.errors","pyexpat.model","abc","importlib","importlib.machinery","jax._src.basearray","jax._src.effects","jaxlib","jaxlib.xla_extension","types"],"hash":"17955162a465cd1a57dd70b42c5587d1a3596629","id":"jax._src.state.discharge","ignore_all":true,"interface_hash":"40a868f67ec29860435ce570d831fa9c52108630","mtime":1,"options":{"allow_redefinition":false,"allow_untyped_globals":false,"always_false":[],"always_true":[],"bazel":false,"check_untyped_defs":true,"disable_bytearray_promotion":false,"disable_error_code":[],"disable_memoryview_promotion":false,"disabled_error_codes":[],"disallow_any_decorated":false,"disallow_any_explicit":false,"disallow_any_expr":false,"disallow_any_generics":true,"disallow_any_unimported":false,"disallow_incomplete_defs":true,"disallow_subclassing_any":true,"disallow_untyped_calls":true,"disallow_untyped_decorators":true,"disallow_untyped_defs":true,"enable_error_code":[],"enabled_error_codes":[],"extra_checks":true,"follow_imports":"silent","follow_imports_for_stubs":false,"ignore_errors":false,"ignore_missing_imports":false,"implicit_optional":false,"implicit_reexport":false,"local_partial_types":false,"mypyc":false,"old_type_inference":false,"platform":"linux","plugins":[],"strict_concatenate":false,"strict_equality":true,"strict_optional":true,"warn_no_return":true,"warn_return_any":true,"warn_unreachable":false,"warn_unused_ignores":true},"path":"/gnu/store/mp4iz1w8i5msmdqrwhiscr2fafv7ykg0-profile/lib/python3.10/site-packages/jax/_src/state/discharge.py","plugin_data":null,"size":37163,"suppressed":[],"version_id":"1.13.0"}