{".class":"MypyFile","_fullname":"ott.tools.soft_sort","future_import_flags":[],"is_partial_stub_package":false,"is_stub":false,"names":{".class":"SymbolTable","Any":{".class":"SymbolTableNode","cross_ref":"typing.Any","kind":"Gdef","module_hidden":true,"module_public":false},"Callable":{".class":"SymbolTableNode","cross_ref":"typing.Callable","kind":"Gdef","module_hidden":true,"module_public":false},"Func_t":{".class":"SymbolTableNode","kind":"Gdef","module_public":false,"node":{".class":"TypeAlias","alias_tvars":[],"column":0,"fullname":"ott.tools.soft_sort.Func_t","line":34,"no_args":false,"normalized":false,"python_3_12_type_alias":false,"target":{".class":"CallableType","arg_kinds":[0],"arg_names":[null],"arg_types":["jax._src.basearray.Array"],"bound_args":[],"def_extras":{},"fallback":"builtins.function","from_concatenate":false,"implicit":false,"imprecise_arg_kinds":false,"is_ellipsis_args":false,"name":null,"ret_type":"jax._src.basearray.Array","type_guard":null,"type_is":null,"unpack_kwargs":false,"variables":[]}}},"Optional":{".class":"SymbolTableNode","cross_ref":"typing.Optional","kind":"Gdef","module_hidden":true,"module_public":false},"Tuple":{".class":"SymbolTableNode","cross_ref":"typing.Tuple","kind":"Gdef","module_hidden":true,"module_public":false},"Union":{".class":"SymbolTableNode","cross_ref":"typing.Union","kind":"Gdef","module_hidden":true,"module_public":false},"__all__":{".class":"SymbolTableNode","kind":"Gdef","module_public":false,"node":{".class":"Var","flags":["is_inferred","has_explicit_value"],"fullname":"ott.tools.soft_sort.__all__","name":"__all__","type":{".class":"Instance","args":["builtins.str"],"extra_attrs":null,"type_ref":"builtins.list"}}},"__annotations__":{".class":"SymbolTableNode","kind":"Gdef","module_public":false,"node":{".class":"Var","flags":["is_ready"],"fullname":"ott.tools.soft_sort.__annotations__","name":"__annotations__","type":{".class":"Instance","args":["builtins.str",{".class":"AnyType","missing_import_name":null,"source_any":null,"type_of_any":6}],"extra_attrs":null,"type_ref":"builtins.dict"}}},"__doc__":{".class":"SymbolTableNode","kind":"Gdef","module_public":false,"node":{".class":"Var","flags":["is_ready"],"fullname":"ott.tools.soft_sort.__doc__","name":"__doc__","type":"builtins.str"}},"__file__":{".class":"SymbolTableNode","kind":"Gdef","module_public":false,"node":{".class":"Var","flags":["is_ready"],"fullname":"ott.tools.soft_sort.__file__","name":"__file__","type":"builtins.str"}},"__name__":{".class":"SymbolTableNode","kind":"Gdef","module_public":false,"node":{".class":"Var","flags":["is_ready"],"fullname":"ott.tools.soft_sort.__name__","name":"__name__","type":"builtins.str"}},"__package__":{".class":"SymbolTableNode","kind":"Gdef","module_public":false,"node":{".class":"Var","flags":["is_ready"],"fullname":"ott.tools.soft_sort.__package__","name":"__package__","type":"builtins.str"}},"__spec__":{".class":"SymbolTableNode","kind":"Gdef","module_public":false,"node":{".class":"Var","flags":["is_ready"],"fullname":"ott.tools.soft_sort.__spec__","name":"__spec__","type":"importlib.machinery.ModuleSpec"}},"_quantile_normalization":{".class":"SymbolTableNode","kind":"Gdef","module_public":false,"node":{".class":"FuncDef","abstract_status":0,"arg_kinds":[0,0,0,4],"arg_names":["inputs","targets","weights","kwargs"],"dataclass_transform_spec":null,"flags":[],"fullname":"ott.tools.soft_sort._quantile_normalization","name":"_quantile_normalization","type":{".class":"CallableType","arg_kinds":[0,0,0,4],"arg_names":["inputs","targets","weights","kwargs"],"arg_types":["jax._src.basearray.Array","jax._src.basearray.Array","builtins.float",{".class":"AnyType","missing_import_name":null,"source_any":null,"type_of_any":2}],"bound_args":[],"def_extras":{"first_arg":null},"fallback":"builtins.function","from_concatenate":false,"implicit":false,"imprecise_arg_kinds":false,"is_ellipsis_args":false,"name":"_quantile_normalization","ret_type":"jax._src.basearray.Array","type_guard":null,"type_is":null,"unpack_kwargs":false,"variables":[]}}},"_quantize":{".class":"SymbolTableNode","kind":"Gdef","module_public":false,"node":{".class":"FuncDef","abstract_status":0,"arg_kinds":[0,0,4],"arg_names":["inputs","num_q","kwargs"],"dataclass_transform_spec":null,"flags":[],"fullname":"ott.tools.soft_sort._quantize","name":"_quantize","type":{".class":"CallableType","arg_kinds":[0,0,4],"arg_names":["inputs","num_q","kwargs"],"arg_types":["jax._src.basearray.Array","builtins.int",{".class":"AnyType","missing_import_name":null,"source_any":null,"type_of_any":2}],"bound_args":[],"def_extras":{"first_arg":null},"fallback":"builtins.function","from_concatenate":false,"implicit":false,"imprecise_arg_kinds":false,"is_ellipsis_args":false,"name":"_quantize","ret_type":"jax._src.basearray.Array","type_guard":null,"type_is":null,"unpack_kwargs":false,"variables":[]}}},"_ranks":{".class":"SymbolTableNode","kind":"Gdef","module_public":false,"node":{".class":"FuncDef","abstract_status":0,"arg_kinds":[0,0,0,4],"arg_names":["inputs","num_targets","target_weights","kwargs"],"dataclass_transform_spec":null,"flags":[],"fullname":"ott.tools.soft_sort._ranks","name":"_ranks","type":{".class":"CallableType","arg_kinds":[0,0,0,4],"arg_names":["inputs","num_targets","target_weights","kwargs"],"arg_types":["jax._src.basearray.Array",{".class":"AnyType","missing_import_name":null,"source_any":null,"type_of_any":1},{".class":"AnyType","missing_import_name":null,"source_any":null,"type_of_any":1},{".class":"AnyType","missing_import_name":null,"source_any":null,"type_of_any":2}],"bound_args":[],"def_extras":{"first_arg":null},"fallback":"builtins.function","from_concatenate":false,"implicit":false,"imprecise_arg_kinds":false,"is_ellipsis_args":false,"name":"_ranks","ret_type":"jax._src.basearray.Array","type_guard":null,"type_is":null,"unpack_kwargs":false,"variables":[]}}},"_sort":{".class":"SymbolTableNode","kind":"Gdef","module_public":false,"node":{".class":"FuncDef","abstract_status":0,"arg_kinds":[0,0,0,4],"arg_names":["inputs","topk","num_targets","kwargs"],"dataclass_transform_spec":null,"flags":[],"fullname":"ott.tools.soft_sort._sort","name":"_sort","type":{".class":"CallableType","arg_kinds":[0,0,0,4],"arg_names":["inputs","topk","num_targets","kwargs"],"arg_types":["jax._src.basearray.Array","builtins.int",{".class":"UnionType","items":["builtins.int",{".class":"NoneType"}],"uses_pep604_syntax":false},{".class":"AnyType","missing_import_name":null,"source_any":null,"type_of_any":2}],"bound_args":[],"def_extras":{"first_arg":null},"fallback":"builtins.function","from_concatenate":false,"implicit":false,"imprecise_arg_kinds":false,"is_ellipsis_args":false,"name":"_sort","ret_type":"jax._src.basearray.Array","type_guard":null,"type_is":null,"unpack_kwargs":false,"variables":[]}}},"apply_on_axis":{".class":"SymbolTableNode","kind":"Gdef","module_public":false,"node":{".class":"FuncDef","abstract_status":0,"arg_kinds":[0,0,0,2,4],"arg_names":["op","inputs","axis","args","kwargs"],"dataclass_transform_spec":null,"flags":[],"fullname":"ott.tools.soft_sort.apply_on_axis","name":"apply_on_axis","type":{".class":"CallableType","arg_kinds":[0,0,0,2,4],"arg_names":["op","inputs","axis","args","kwargs"],"arg_types":[{".class":"AnyType","missing_import_name":null,"source_any":null,"type_of_any":1},{".class":"AnyType","missing_import_name":null,"source_any":null,"type_of_any":1},{".class":"AnyType","missing_import_name":null,"source_any":null,"type_of_any":1},{".class":"AnyType","missing_import_name":null,"source_any":null,"type_of_any":1},{".class":"AnyType","missing_import_name":null,"source_any":null,"type_of_any":2}],"bound_args":[],"def_extras":{"first_arg":null},"fallback":"builtins.function","from_concatenate":false,"implicit":false,"imprecise_arg_kinds":false,"is_ellipsis_args":false,"name":"apply_on_axis","ret_type":"jax._src.basearray.Array","type_guard":null,"type_is":null,"unpack_kwargs":false,"variables":[]}}},"costs":{".class":"SymbolTableNode","cross_ref":"ott.geometry.costs","kind":"Gdef","module_hidden":true,"module_public":false},"functools":{".class":"SymbolTableNode","cross_ref":"functools","kind":"Gdef","module_hidden":true,"module_public":false},"initializers":{".class":"SymbolTableNode","cross_ref":"ott.initializers.linear.initializers","kind":"Gdef","module_hidden":true,"module_public":false},"jax":{".class":"SymbolTableNode","cross_ref":"jax","kind":"Gdef","module_hidden":true,"module_public":false},"jnp":{".class":"SymbolTableNode","cross_ref":"jax.numpy","kind":"Gdef","module_hidden":true,"module_public":false},"jtu":{".class":"SymbolTableNode","cross_ref":"jax.tree_util","kind":"Gdef","module_hidden":true,"module_public":false},"linear":{".class":"SymbolTableNode","cross_ref":"ott.solvers.linear","kind":"Gdef","module_hidden":true,"module_public":false},"linear_problem":{".class":"SymbolTableNode","cross_ref":"ott.problems.linear.linear_problem","kind":"Gdef","module_hidden":true,"module_public":false},"multivariate_cdf_quantile_maps":{".class":"SymbolTableNode","kind":"Gdef","node":{".class":"FuncDef","abstract_status":0,"arg_kinds":[0,1,1,1,1,1,1,1,4],"arg_names":["inputs","target_sampler","rng","num_target_samples","cost_fn","epsilon","input_weights","target_weights","kwargs"],"dataclass_transform_spec":null,"flags":[],"fullname":"ott.tools.soft_sort.multivariate_cdf_quantile_maps","name":"multivariate_cdf_quantile_maps","type":{".class":"CallableType","arg_kinds":[0,1,1,1,1,1,1,1,4],"arg_names":["inputs","target_sampler","rng","num_target_samples","cost_fn","epsilon","input_weights","target_weights","kwargs"],"arg_types":["jax._src.basearray.Array",{".class":"UnionType","items":[{".class":"CallableType","arg_kinds":[0,0],"arg_names":[null,null],"arg_types":["jax._src.basearray.Array",{".class":"TupleType","implicit":false,"items":["builtins.int","builtins.int"],"partial_fallback":{".class":"Instance","args":[{".class":"AnyType","missing_import_name":null,"source_any":null,"type_of_any":6}],"extra_attrs":null,"type_ref":"builtins.tuple"}}],"bound_args":[],"def_extras":{},"fallback":"builtins.function","from_concatenate":false,"implicit":false,"imprecise_arg_kinds":false,"is_ellipsis_args":false,"name":null,"ret_type":"jax._src.basearray.Array","type_guard":null,"type_is":null,"unpack_kwargs":false,"variables":[]},{".class":"NoneType"}],"uses_pep604_syntax":false},{".class":"UnionType","items":["jax._src.basearray.Array",{".class":"NoneType"}],"uses_pep604_syntax":false},{".class":"UnionType","items":["builtins.int",{".class":"NoneType"}],"uses_pep604_syntax":false},{".class":"UnionType","items":["ott.geometry.costs.CostFn",{".class":"NoneType"}],"uses_pep604_syntax":false},{".class":"UnionType","items":["builtins.float",{".class":"NoneType"}],"uses_pep604_syntax":false},{".class":"UnionType","items":["jax._src.basearray.Array",{".class":"NoneType"}],"uses_pep604_syntax":false},{".class":"UnionType","items":["jax._src.basearray.Array",{".class":"NoneType"}],"uses_pep604_syntax":false},{".class":"AnyType","missing_import_name":null,"source_any":null,"type_of_any":2}],"bound_args":[],"def_extras":{"first_arg":null},"fallback":"builtins.function","from_concatenate":false,"implicit":false,"imprecise_arg_kinds":false,"is_ellipsis_args":false,"name":"multivariate_cdf_quantile_maps","ret_type":{".class":"TupleType","implicit":false,"items":[{".class":"TypeAliasType","args":[],"type_ref":"ott.tools.soft_sort.Func_t"},{".class":"TypeAliasType","args":[],"type_ref":"ott.tools.soft_sort.Func_t"}],"partial_fallback":{".class":"Instance","args":[{".class":"AnyType","missing_import_name":null,"source_any":null,"type_of_any":6}],"extra_attrs":null,"type_ref":"builtins.tuple"}},"type_guard":null,"type_is":null,"unpack_kwargs":false,"variables":[]}}},"np":{".class":"SymbolTableNode","cross_ref":"numpy","kind":"Gdef","module_hidden":true,"module_public":false},"pointcloud":{".class":"SymbolTableNode","cross_ref":"ott.geometry.pointcloud","kind":"Gdef","module_hidden":true,"module_public":false},"quantile":{".class":"SymbolTableNode","kind":"Gdef","node":{".class":"FuncDef","abstract_status":0,"arg_kinds":[0,0,1,1,4],"arg_names":["inputs","q","axis","weight","kwargs"],"dataclass_transform_spec":null,"flags":[],"fullname":"ott.tools.soft_sort.quantile","name":"quantile","type":{".class":"CallableType","arg_kinds":[0,0,1,1,4],"arg_names":["inputs","q","axis","weight","kwargs"],"arg_types":["jax._src.basearray.Array",{".class":"UnionType","items":["builtins.float","jax._src.basearray.Array",{".class":"NoneType"}],"uses_pep604_syntax":false},{".class":"UnionType","items":["builtins.int",{".class":"Instance","args":["builtins.int"],"extra_attrs":null,"type_ref":"builtins.tuple"}],"uses_pep604_syntax":false},{".class":"UnionType","items":["builtins.float","jax._src.basearray.Array",{".class":"NoneType"}],"uses_pep604_syntax":false},{".class":"AnyType","missing_import_name":null,"source_any":null,"type_of_any":2}],"bound_args":[],"def_extras":{"first_arg":null},"fallback":"builtins.function","from_concatenate":false,"implicit":false,"imprecise_arg_kinds":false,"is_ellipsis_args":false,"name":"quantile","ret_type":"jax._src.basearray.Array","type_guard":null,"type_is":null,"unpack_kwargs":false,"variables":[]}}},"quantile_normalization":{".class":"SymbolTableNode","kind":"Gdef","node":{".class":"FuncDef","abstract_status":0,"arg_kinds":[0,0,1,1,4],"arg_names":["inputs","targets","weights","axis","kwargs"],"dataclass_transform_spec":null,"flags":[],"fullname":"ott.tools.soft_sort.quantile_normalization","name":"quantile_normalization","type":{".class":"CallableType","arg_kinds":[0,0,1,1,4],"arg_names":["inputs","targets","weights","axis","kwargs"],"arg_types":["jax._src.basearray.Array","jax._src.basearray.Array",{".class":"UnionType","items":["jax._src.basearray.Array",{".class":"NoneType"}],"uses_pep604_syntax":false},"builtins.int",{".class":"AnyType","missing_import_name":null,"source_any":null,"type_of_any":2}],"bound_args":[],"def_extras":{"first_arg":null},"fallback":"builtins.function","from_concatenate":false,"implicit":false,"imprecise_arg_kinds":false,"is_ellipsis_args":false,"name":"quantile_normalization","ret_type":"jax._src.basearray.Array","type_guard":null,"type_is":null,"unpack_kwargs":false,"variables":[]}}},"quantize":{".class":"SymbolTableNode","kind":"Gdef","node":{".class":"FuncDef","abstract_status":0,"arg_kinds":[0,1,1,4],"arg_names":["inputs","num_levels","axis","kwargs"],"dataclass_transform_spec":null,"flags":[],"fullname":"ott.tools.soft_sort.quantize","name":"quantize","type":{".class":"CallableType","arg_kinds":[0,1,1,4],"arg_names":["inputs","num_levels","axis","kwargs"],"arg_types":["jax._src.basearray.Array","builtins.int","builtins.int",{".class":"AnyType","missing_import_name":null,"source_any":null,"type_of_any":2}],"bound_args":[],"def_extras":{"first_arg":null},"fallback":"builtins.function","from_concatenate":false,"implicit":false,"imprecise_arg_kinds":false,"is_ellipsis_args":false,"name":"quantize","ret_type":"jax._src.basearray.Array","type_guard":null,"type_is":null,"unpack_kwargs":false,"variables":[]}}},"ranks":{".class":"SymbolTableNode","kind":"Gdef","node":{".class":"FuncDef","abstract_status":0,"arg_kinds":[0,1,1,1,4],"arg_names":["inputs","axis","num_targets","target_weights","kwargs"],"dataclass_transform_spec":null,"flags":[],"fullname":"ott.tools.soft_sort.ranks","name":"ranks","type":{".class":"CallableType","arg_kinds":[0,1,1,1,4],"arg_names":["inputs","axis","num_targets","target_weights","kwargs"],"arg_types":["jax._src.basearray.Array","builtins.int",{".class":"UnionType","items":["builtins.int",{".class":"NoneType"}],"uses_pep604_syntax":false},{".class":"UnionType","items":["jax._src.basearray.Array",{".class":"NoneType"}],"uses_pep604_syntax":false},{".class":"AnyType","missing_import_name":null,"source_any":null,"type_of_any":2}],"bound_args":[],"def_extras":{"first_arg":null},"fallback":"builtins.function","from_concatenate":false,"implicit":false,"imprecise_arg_kinds":false,"is_ellipsis_args":false,"name":"ranks","ret_type":"jax._src.basearray.Array","type_guard":null,"type_is":null,"unpack_kwargs":false,"variables":[]}}},"sinkhorn":{".class":"SymbolTableNode","cross_ref":"ott.solvers.linear.sinkhorn","kind":"Gdef","module_hidden":true,"module_public":false},"sort":{".class":"SymbolTableNode","kind":"Gdef","node":{".class":"FuncDef","abstract_status":0,"arg_kinds":[0,1,1,1,4],"arg_names":["inputs","axis","topk","num_targets","kwargs"],"dataclass_transform_spec":null,"flags":[],"fullname":"ott.tools.soft_sort.sort","name":"sort","type":{".class":"CallableType","arg_kinds":[0,1,1,1,4],"arg_names":["inputs","axis","topk","num_targets","kwargs"],"arg_types":["jax._src.basearray.Array","builtins.int","builtins.int",{".class":"UnionType","items":["builtins.int",{".class":"NoneType"}],"uses_pep604_syntax":false},{".class":"AnyType","missing_import_name":null,"source_any":null,"type_of_any":2}],"bound_args":[],"def_extras":{"first_arg":null},"fallback":"builtins.function","from_concatenate":false,"implicit":false,"imprecise_arg_kinds":false,"is_ellipsis_args":false,"name":"sort","ret_type":"jax._src.basearray.Array","type_guard":null,"type_is":null,"unpack_kwargs":false,"variables":[]}}},"sort_with":{".class":"SymbolTableNode","kind":"Gdef","node":{".class":"FuncDef","abstract_status":0,"arg_kinds":[0,0,1,4],"arg_names":["inputs","criterion","topk","kwargs"],"dataclass_transform_spec":null,"flags":[],"fullname":"ott.tools.soft_sort.sort_with","name":"sort_with","type":{".class":"CallableType","arg_kinds":[0,0,1,4],"arg_names":["inputs","criterion","topk","kwargs"],"arg_types":["jax._src.basearray.Array","jax._src.basearray.Array","builtins.int",{".class":"AnyType","missing_import_name":null,"source_any":null,"type_of_any":2}],"bound_args":[],"def_extras":{"first_arg":null},"fallback":"builtins.function","from_concatenate":false,"implicit":false,"imprecise_arg_kinds":false,"is_ellipsis_args":false,"name":"sort_with","ret_type":"jax._src.basearray.Array","type_guard":null,"type_is":null,"unpack_kwargs":false,"variables":[]}}},"topk_mask":{".class":"SymbolTableNode","kind":"Gdef","node":{".class":"FuncDef","abstract_status":0,"arg_kinds":[0,1,1,4],"arg_names":["inputs","axis","k","kwargs"],"dataclass_transform_spec":null,"flags":[],"fullname":"ott.tools.soft_sort.topk_mask","name":"topk_mask","type":{".class":"CallableType","arg_kinds":[0,1,1,4],"arg_names":["inputs","axis","k","kwargs"],"arg_types":["jax._src.basearray.Array","builtins.int","builtins.int",{".class":"AnyType","missing_import_name":null,"source_any":null,"type_of_any":2}],"bound_args":[],"def_extras":{"first_arg":null},"fallback":"builtins.function","from_concatenate":false,"implicit":false,"imprecise_arg_kinds":false,"is_ellipsis_args":false,"name":"topk_mask","ret_type":"jax._src.basearray.Array","type_guard":null,"type_is":null,"unpack_kwargs":false,"variables":[]}}},"transport_for_sort":{".class":"SymbolTableNode","kind":"Gdef","module_public":false,"node":{".class":"FuncDef","abstract_status":0,"arg_kinds":[0,1,1,1,1,4],"arg_names":["inputs","weights","target_weights","squashing_fun","epsilon","kwargs"],"dataclass_transform_spec":null,"flags":[],"fullname":"ott.tools.soft_sort.transport_for_sort","name":"transport_for_sort","type":{".class":"CallableType","arg_kinds":[0,1,1,1,1,4],"arg_names":["inputs","weights","target_weights","squashing_fun","epsilon","kwargs"],"arg_types":["jax._src.basearray.Array",{".class":"UnionType","items":["jax._src.basearray.Array",{".class":"NoneType"}],"uses_pep604_syntax":false},{".class":"UnionType","items":["jax._src.basearray.Array",{".class":"NoneType"}],"uses_pep604_syntax":false},{".class":"UnionType","items":[{".class":"CallableType","arg_kinds":[0],"arg_names":[null],"arg_types":["jax._src.basearray.Array"],"bound_args":[],"def_extras":{},"fallback":"builtins.function","from_concatenate":false,"implicit":false,"imprecise_arg_kinds":false,"is_ellipsis_args":false,"name":null,"ret_type":"jax._src.basearray.Array","type_guard":null,"type_is":null,"unpack_kwargs":false,"variables":[]},{".class":"NoneType"}],"uses_pep604_syntax":false},"builtins.float",{".class":"AnyType","missing_import_name":null,"source_any":null,"type_of_any":2}],"bound_args":[],"def_extras":{"first_arg":null},"fallback":"builtins.function","from_concatenate":false,"implicit":false,"imprecise_arg_kinds":false,"is_ellipsis_args":false,"name":"transport_for_sort","ret_type":{".class":"TypeAliasType","args":[],"type_ref":"ott.solvers.linear.sinkhorn.SinkhornOutput"},"type_guard":null,"type_is":null,"unpack_kwargs":false,"variables":[]}}},"utils":{".class":"SymbolTableNode","cross_ref":"ott.utils","kind":"Gdef","module_hidden":true,"module_public":false}},"path":"/gnu/store/mp4iz1w8i5msmdqrwhiscr2fafv7ykg0-profile/lib/python3.10/site-packages/ott/tools/soft_sort.py"}